[
  {
    "id": "bc59b997-4b98-4e1d-900f-325bc9791238",
    "data": [
      {
        "text": "classify using ",
        "userDefined": false
      },
      {
        "text": "regression",
        "alias": "Algorithms",
        "meta": "@Algorithms",
        "userDefined": true
      }
    ],
    "isTemplate": false,
    "count": 0,
    "updated": 1547445192
  },
  {
    "id": "d1c7fe52-bd59-4d9a-b5c2-74445913601f",
    "data": [
      {
        "text": "classifier is ",
        "userDefined": false
      },
      {
        "text": "LinearSVC",
        "alias": "Algorithms",
        "meta": "@Algorithms",
        "userDefined": true
      }
    ],
    "isTemplate": false,
    "count": 0,
    "updated": 1546086608
  },
  {
    "id": "3d861743-4043-4602-9cd0-ded9472aa028",
    "data": [
      {
        "text": "clf \u003d ",
        "userDefined": false
      },
      {
        "text": "Logistic Regression",
        "alias": "Algorithms",
        "meta": "@Algorithms",
        "userDefined": true
      }
    ],
    "isTemplate": false,
    "count": 0,
    "updated": 1546086608
  },
  {
    "id": "feb27aa6-f143-42bb-81f4-9dff3be84eef",
    "data": [
      {
        "text": "classify data frame using ",
        "userDefined": false
      },
      {
        "text": "MultinomialNB",
        "alias": "Algorithms",
        "meta": "@Algorithms",
        "userDefined": true
      }
    ],
    "isTemplate": false,
    "count": 0,
    "updated": 1546086608
  },
  {
    "id": "4acd1b44-95f3-4b70-a9cf-4cb65365d5b7",
    "data": [
      {
        "text": "import ",
        "userDefined": false
      },
      {
        "text": "KNN",
        "alias": "Algorithms",
        "meta": "@Algorithms",
        "userDefined": false
      }
    ],
    "isTemplate": false,
    "count": 1,
    "updated": 1545806762
  },
  {
    "id": "73cc52cf-3c9e-4e93-967b-f30c2a68d366",
    "data": [
      {
        "text": "Algorithm \u003d ",
        "userDefined": false
      },
      {
        "text": "DTC",
        "alias": "Algorithms",
        "meta": "@Algorithms",
        "userDefined": false
      }
    ],
    "isTemplate": false,
    "count": 0,
    "updated": 1545737548
  },
  {
    "id": "aa99c4c2-e3cf-49a3-9750-531d330b69eb",
    "data": [
      {
        "text": "Apply ",
        "userDefined": false
      },
      {
        "text": "K-Means",
        "alias": "Algorithms",
        "meta": "@Algorithms",
        "userDefined": false
      }
    ],
    "isTemplate": false,
    "count": 0,
    "updated": 1545737334
  },
  {
    "id": "cefa52cf-1115-4228-8b76-6c3f8e37780e",
    "data": [
      {
        "text": "use ",
        "userDefined": false
      },
      {
        "text": "KNN",
        "alias": "Algorithms",
        "meta": "@Algorithms",
        "userDefined": false
      },
      {
        "text": " classifiction",
        "userDefined": false
      }
    ],
    "isTemplate": false,
    "count": 0,
    "updated": 1545737202
  },
  {
    "id": "cc993a88-c275-47dd-98bd-cfb041eada62",
    "data": [
      {
        "text": "By applying ",
        "userDefined": false
      },
      {
        "text": "support vector machine",
        "alias": "Algorithms",
        "meta": "@Algorithms",
        "userDefined": false
      }
    ],
    "isTemplate": false,
    "count": 0,
    "updated": 1545737202
  },
  {
    "id": "8db3eb10-5749-4145-ac58-8282f5f4c432",
    "data": [
      {
        "text": "use ",
        "userDefined": false
      },
      {
        "text": "ANN",
        "alias": "Algorithms",
        "meta": "@Algorithms",
        "userDefined": false
      }
    ],
    "isTemplate": false,
    "count": 0,
    "updated": 1545737202
  }
]